f2llm/__init__.py
f2llm/_version.py
f2llm/cli.py
f2llm-0.1.5.dist-info/licenses/LICENSE
f2llm-0.1.5.dist-info/METADATA
f2llm-0.1.5.dist-info/WHEEL
f2llm-0.1.5.dist-info/entry_points.txt
f2llm-0.1.5.dist-info/top_level.txt
f2llm-0.1.5.dist-info/RECORD
