Metadata-Version: 2.4
Name: f2llm
Version: 0.1.5
Summary: A CLI tool to parse files and create LLM prompts
Author: Mate Dravucz
License: MIT
Project-URL: Homepage, https://github.com/mattdravucz/f2llm
Project-URL: Issues, https://github.com/mattdravucz/f2llm/issues
Keywords: cli,llm,file parsing
Classifier: Programming Language :: Python :: 3
Classifier: License :: OSI Approved :: MIT License
Classifier: Operating System :: OS Independent
Requires-Python: >=3.9
License-File: LICENSE
Requires-Dist: pathspec>=0.11.1
Dynamic: license-file
